[{"domain": ".2gis.ru", "expiry": 1721913915, "httpOnly": false, "name": "_ga", "path": "/", "sameSite": "Lax", "secure": false, "value": "GA1.1.690621309.1687353904"}, {"domain": ".2gis.ru", "expiry": 1721913915, "httpOnly": false, "name": "_ga_RYXLFPYJB8", "path": "/", "sameSite": "Lax", "secure": false, "value": "GS1.1.1687353904.1.1.1687353915.0.0.0"}, {"domain": ".2gis.ru", "expiry": 1687425907, "httpOnly": false, "name": "_ym_isad", "path": "/", "sameSite": "None", "secure": true, "value": "2"}, {"domain": ".2gis.ru", "expiry": 1718889904, "httpOnly": false, "name": "_ym_d", "path": "/", "sameSite": "None", "secure": true, "value": "1687353905"}, {"domain": ".2gis.ru", "expiry": 1716125115, "httpOnly": false, "name": "tmr_lvid", "path": "/", "sameSite": "Lax", "secure": false, "value": "059cdd54225dc211a79bda7b29bfd502"}, {"domain": ".2gis.ru", "expiry": 1721913904, "httpOnly": false, "name": "_2gis_webapi_user", "path": "/", "sameSite": "Lax", "secure": false, "value": "81062805-46ec-49bd-96cd-1ca305cccab6"}, {"domain": ".2gis.ru", "expiry": 1687353964, "httpOnly": false, "name": "_gat_online5", "path": "/", "sameSite": "Lax", "secure": false, "value": "1"}, {"domain": ".2gis.ru", "expiry": 1687440314, "httpOnly": false, "name": "_gid", "path": "/", "sameSite": "Lax", "secure": false, "value": "GA1.2.1833490270.1687353905"}, {"domain": ".2gis.ru", "expiry": 1716125115, "httpOnly": false, "name": "tmr_lvidTS", "path": "/", "sameSite": "Lax", "secure": false, "value": "1687353904542"}, {"domain": ".2gis.ru", "expiry": 1718889904, "httpOnly": false, "name": "_ym_uid", "path": "/", "sameSite": "None", "secure": true, "value": "1687353905958686249"}, {"domain": ".2gis.ru", "httpOnly": false, "name": "_2gis_webapi_session", "path": "/", "sameSite": "Lax", "secure": false, "value": "d803ce48-e4ef-4d71-9e80-98d108abc40e"}, {"domain": "2gis.ru", "expiry": 1721913904, "httpOnly": false, "name": "spid", "path": "/", "sameSite": "None", "secure": true, "value": "1687353903647_e549c32debda510738c4e3271054b457_f71sfk2vnv2j43h1"}]